MANIFEST.in
setup.py
hello_world_source_code/Ahoy.wav
hello_world_source_code/AvastGotIt.wav
hello_world_source_code/DozerBlue.png
hello_world_source_code/DozerRed.png
hello_world_source_code/Listing_11-6.py
hello_world_source_code/Listing_11-7.py
hello_world_source_code/Listing_13-1.py
hello_world_source_code/Listing_13-2.py
hello_world_source_code/Listing_13-3.py
hello_world_source_code/Listing_13-4.py
hello_world_source_code/Listing_13-5.py
hello_world_source_code/Listing_13-6.py
hello_world_source_code/Listing_13-7.py
hello_world_source_code/Listing_14-1.py
hello_world_source_code/Listing_14-2.py
hello_world_source_code/Listing_14-3.py
hello_world_source_code/Listing_14-4.py
hello_world_source_code/Listing_14-5.py
hello_world_source_code/Listing_14-6.py
hello_world_source_code/Listing_15-1.py
hello_world_source_code/Listing_15-2.py
hello_world_source_code/Listing_15-3.py
hello_world_source_code/Listing_16-1.py
hello_world_source_code/Listing_16-10.py
hello_world_source_code/Listing_16-11.py
hello_world_source_code/Listing_16-12.py
hello_world_source_code/Listing_16-13.py
hello_world_source_code/Listing_16-14.py
hello_world_source_code/Listing_16-15.py
hello_world_source_code/Listing_16-16.py
hello_world_source_code/Listing_16-2.py
hello_world_source_code/Listing_16-3.py
hello_world_source_code/Listing_16-4.py
hello_world_source_code/Listing_16-5.py
hello_world_source_code/Listing_16-6.py
hello_world_source_code/Listing_16-7.py
hello_world_source_code/Listing_16-8.py
hello_world_source_code/Listing_17-1.py
hello_world_source_code/Listing_17-2.py
hello_world_source_code/Listing_17-3.py
hello_world_source_code/Listing_17-4.py
hello_world_source_code/Listing_18-1.py
hello_world_source_code/Listing_18-2.py
hello_world_source_code/Listing_18-3.py
hello_world_source_code/Listing_18-4.py
hello_world_source_code/Listing_18-5.py
hello_world_source_code/Listing_19-1.py
hello_world_source_code/Listing_19-2.py
hello_world_source_code/Listing_19-3.py
hello_world_source_code.egg-info/PKG-INFO
hello_world_source_code.egg-info/SOURCES.txt
hello_world_source_code.egg-info/dependency_links.txt
hello_world_source_code.egg-info/requires.txt
hello_world_source_code.egg-info/top_level.txt
